pylarid.cpython-312-darwin.so
pylarid-0.1.dev0.dist-info/METADATA
pylarid-0.1.dev0.dist-info/WHEEL
pylarid-0.1.dev0.dist-info/entry_points.txt
pylarid-0.1.dev0.dist-info/licenses/LICENSE.txt
pylarid-0.1.dev0.dist-info/RECORD
