Metadata-Version: 2.1
Name: pylarid
Version: 0.1.dev0
Summary: Load Arrays of Imaging Data
Keywords: mri fmri
Author-Email: Jeffrey Michael Engelmann <jme2041@icloud.com>
License: MIT License
Classifier: Development Status :: 3 - Alpha
Classifier: License :: OSI Approved :: MIT License
Classifier: Programming Language :: C++
Classifier: Programming Language :: Python :: 3
Classifier: Programming Language :: Python :: Implementation :: CPython
Classifier: Operating System :: MacOS :: MacOS X
Classifier: Operating System :: Microsoft :: Windows :: Windows 11
Classifier: Operating System :: POSIX :: Linux
Classifier: Natural Language :: English
Classifier: Environment :: Console
Classifier: Intended Audience :: Science/Research
Classifier: Topic :: Scientific/Engineering :: Bio-Informatics
Classifier: Topic :: Scientific/Engineering :: Image Processing
Project-URL: Repository, https://github.com/jme2041/pylarid.git
License-File: LICENSE.txt
